[
    {
        "model": "testapp.Profile",
        "pk": 1,
        "fields": {
            "real_name": "Egon Spengler",
            "user_id":"W012A3CDE",
            "timezone":"America/Los_Angeles"
        }
    },
    {
        "model": "testapp.Profile",
        "pk": 2,
        "fields": {
            "real_name": "Glinda Southgood",
            "user_id": "W07QCRPA4",
            "timezone": "Asia/Kolkata"
        }
    },

    {
        "model": "testapp.ProfileActivity",
        "pk": 1,
        "fields": {
            "activity_start_date": "2020-03-29T11:40:59.083343Z",
            "activity_end_date": "2020-03-29T11:40:59.083343Z",
            "profile": 1
        }
    },
    {
        "model": "testapp.ProfileActivity",
        "pk": 2,
        "fields": {
            "activity_start_date": "2020-03-29T11:40:59.083343Z",
            "activity_end_date": "2020-03-29T11:40:59.083343Z",
            "profile": 1
        }
    },
    {
        "model": "testapp.ProfileActivity",
        "pk": 3,
        "fields": {
            "activity_start_date": "2020-03-29T11:40:59.083343Z",
            "activity_end_date": "2020-03-29T11:40:59.083343Z",
            "profile": 1
        }
    },
    {
        "model": "testapp.ProfileActivity",
        "pk": 4,
        "fields": {
            "activity_start_date": "2020-03-29T11:40:59.083343Z",
            "activity_end_date": "2020-03-29T11:40:59.083343Z",
            "profile": 2
        }
    },
    {
        "model": "testapp.ProfileActivity",
        "pk": 5,
        "fields": {
            "activity_start_date": "2020-03-29T11:40:59.083343Z",
            "activity_end_date": "2020-03-29T11:40:59.083343Z",
            "profile": 2
        }
    },
    {
        "model": "testapp.ProfileActivity",
        "pk": 6,
        "fields": {
            "activity_start_date": "2020-03-29T11:40:59.083343Z",
            "activity_end_date": "2020-03-29T11:40:59.083343Z",
            "profile": 2
        }
    }
]